flounder/__init__.py
flounder/py.typed
flounder/score.py
flounder_score-1.3.0.dist-info/WHEEL
flounder_score-1.3.0.dist-info/METADATA
flounder_score-1.3.0.dist-info/RECORD
