Metadata-Version: 2.4
Name: flounder-score
Version: 1.3.0
Summary: Flounder score library
Keywords: library,dna,genetics,bioinformatics,joke
Author: Dave Pearson
Author-email: Dave Pearson <davep@davep.org>
License-Expression: MIT
Classifier: Development Status :: 5 - Production/Stable
Classifier: Operating System :: OS Independent
Classifier: Programming Language :: Python :: 3.9
Classifier: Programming Language :: Python :: 3.10
Classifier: Programming Language :: Python :: 3.11
Classifier: Programming Language :: Python :: 3.12
Classifier: Programming Language :: Python :: 3.13
Classifier: Programming Language :: Python :: 3.14
Classifier: Topic :: Software Development :: Libraries
Classifier: Typing :: Typed
Classifier: Intended Audience :: Science/Research
Classifier: Topic :: Scientific/Engineering :: Bio-Informatics
Requires-Python: >=3.9
Project-URL: Discussions, https://github.com/davep/flounder-score/discussions
Project-URL: Documentation, https://flounder-score.davep.dev/
Project-URL: Homepage, https://flounder-score.davep.dev/
Project-URL: Issues, https://github.com/davep/flounder-score/issues
Project-URL: Repository, https://github.com/davep/flounder-score
Project-URL: Source, https://github.com/davep/flounder-score
